[
  {
    "name": "Johnny",
    "surname": "Cash",
    "email": "johny@cash.com",
    "dob": "26-02-1932",
    "ID": "11s20saxgkig47njw",
    "projects": []
  },
  {
    "name": "Elvis",
    "surname": "Presley",
    "email": "elvis@elvis.com",
    "dob": "08-01-1935",
    "ID": "11s20sb1ukig4b8uh",
    "projects": []
  },
  {
    "name": "Roy",
    "surname": "Orbison",
    "email": "roy@orbison.com",
    "dob": "24-04-1936",
    "ID": "11s20scklkig587zm",
    "projects": []
  }
]
